{
    "trungtin": {
        "20220713233603": {
            "hotel": "hcmue",
            "order_time": "2022-07-13 23:36:03",
            "no": [
                "201"
            ],
            "checkin": "2022-08-01",
            "checkout": "2022-08-04"
        },
        "202271485330": {
            "hotel": "hcmus",
            "order_time": "2022-07-14 08:53:30",
            "no": [
                "101"
            ],
            "checkin": "2022-08-01",
            "checkout": "2022-08-05"
        }
    },
    "hongphuc": {
        "20225393023": {
            "hotel": "hcmus",
            "order_time": "2022-05-03 09:30:23",
            "no": [
                "102"
            ],
            "checkin": "2022-10-11",
            "checkout": "2022-10-15"
        }
    },
    "caoluan": {}
}